{
  "hash": "d96d3b71",
  "configHash": "54303eb3",
  "lockfileHash": "36b10ced",
  "browserHash": "0a6abf77",
  "optimized": {
    "react/jsx-dev-runtime": {
      "src": "../../node_modules/react/jsx-dev-runtime.js",
      "file": "react_jsx-dev-runtime.js",
      "fileHash": "f9a088e0",
      "needsInterop": true
    },
    "react": {
      "src": "../../node_modules/react/index.js",
      "file": "react.js",
      "fileHash": "1dc67698",
      "needsInterop": true
    },
    "react-dom/client": {
      "src": "../../node_modules/react-dom/client.js",
      "file": "react-dom_client.js",
      "fileHash": "c3147813",
      "needsInterop": true
    },
    "react-router-dom": {
      "src": "../../node_modules/react-router-dom/dist/index.mjs",
      "file": "react-router-dom.js",
      "fileHash": "78664e0d",
      "needsInterop": false
    },
    "dayjs": {
      "src": "../../node_modules/dayjs/dayjs.min.js",
      "file": "dayjs.js",
      "fileHash": "207feecc",
      "needsInterop": true
    },
    "recharts": {
      "src": "../../node_modules/recharts/es6/index.js",
      "file": "recharts.js",
      "fileHash": "db10f001",
      "needsInterop": false
    },
    "ag-grid-react": {
      "src": "../../node_modules/ag-grid-react/dist/package/index.esm.mjs",
      "file": "ag-grid-react.js",
      "fileHash": "8783b1fc",
      "needsInterop": false
    },
    "ag-grid-community": {
      "src": "../../node_modules/ag-grid-community/dist/package/main.esm.mjs",
      "file": "ag-grid-community.js",
      "fileHash": "36bf65d8",
      "needsInterop": false
    }
  },
  "chunks": {
    "chunk-5HNGYYSW": {
      "file": "chunk-5HNGYYSW.js"
    },
    "chunk-TVFQMRVC": {
      "file": "chunk-TVFQMRVC.js"
    },
    "chunk-G6FRJL7C": {
      "file": "chunk-G6FRJL7C.js"
    },
    "chunk-G3PMV62Z": {
      "file": "chunk-G3PMV62Z.js"
    }
  }
}